bpeasy-0.1.6.dist-info/METADATA
bpeasy-0.1.6.dist-info/WHEEL
bpeasy-0.1.6.dist-info/licenses/LICENSE
bpeasy/__init__.py
bpeasy/bpeasy.cpython-38-powerpc64le-linux-gnu.so
bpeasy/bpeasy.pyi
bpeasy/convert.py
bpeasy/tokenizer.py
bpeasy-0.1.6.dist-info/RECORD
