Metadata-Version: 2.4
Name: bpeasy
Version: 0.1.6
Classifier: Programming Language :: Rust
Classifier: Programming Language :: Python :: Implementation :: CPython
Classifier: Programming Language :: Python :: Implementation :: PyPy
Classifier: Programming Language :: Python :: 3.8
Classifier: Programming Language :: Python :: 3.9
Classifier: Programming Language :: Python :: 3.10
Classifier: Programming Language :: Python :: 3.11
Classifier: Programming Language :: Python :: 3.12
Classifier: Programming Language :: Python :: 3.13
Classifier: License :: OSI Approved :: MIT License
Requires-Dist: tiktoken>=0.4.0
Requires-Dist: pytest ; extra == 'dev'
Requires-Dist: pytest-cov ; extra == 'dev'
Requires-Dist: black ; extra == 'dev'
Requires-Dist: tokenizers ; extra == 'dev'
Requires-Dist: tqdm ; extra == 'dev'
Provides-Extra: dev
License-File: LICENSE
Summary: Fast bare-bones BPE for modern tokenizer training
Keywords: tokenizer,tokenization,bpe
Author-email: Gautier Dagan <<gautier.dagan@ed.ac.uk>>
License: MIT
Requires-Python: >=3.8
